__init__.py
maddpkg.py
optimal_bandwidth.py
maddpkg-0.5.7.dist-info/LICENSE.md
maddpkg-0.5.7.dist-info/METADATA
maddpkg-0.5.7.dist-info/WHEEL
maddpkg-0.5.7.dist-info/top_level.txt
maddpkg-0.5.7.dist-info/RECORD
