Metadata-Version: 2.1
Name: maddpkg
Version: 0.5.7
Summary: A Python package to compute MADD metric-related functions
Home-page: https://github.com/melinaverger/MADDpkg
Author: Mélina Verger
Author-email: melina.verger@lip6.fr
License: CC BY-NC 4.0
Classifier: Programming Language :: Python :: 3.10
Classifier: Operating System :: OS Independent
Requires-Python: >=3.10.4
License-File: LICENSE.md
Requires-Dist: scikit-learn
Requires-Dist: pandas
Requires-Dist: numpy
Requires-Dist: seaborn
Requires-Dist: matplotlib
Provides-Extra: dev
Requires-Dist: twine >=4.0.2 ; extra == 'dev'
